odoo/addons/sm_partago_accounting/__init__.py
odoo/addons/sm_partago_accounting/__manifest__.py
odoo/addons/sm_partago_accounting/models/__init__.py
odoo/addons/sm_partago_accounting/models/account_asset.py
odoo/addons/sm_partago_accounting/models/models_sm_member.py
odoo/addons/sm_partago_accounting/views/views_account_asset.xml
odoo/addons/sm_partago_accounting/views/views_members.xml
odoo12_addon_sm_partago_accounting-12.0.0.0.5.dist-info/METADATA
odoo12_addon_sm_partago_accounting-12.0.0.0.5.dist-info/WHEEL
odoo12_addon_sm_partago_accounting-12.0.0.0.5.dist-info/top_level.txt
odoo12_addon_sm_partago_accounting-12.0.0.0.5.dist-info/RECORD
